helloworld.py
gpravada_helloworld-0.0.1.dist-info/LICENSE
gpravada_helloworld-0.0.1.dist-info/METADATA
gpravada_helloworld-0.0.1.dist-info/WHEEL
gpravada_helloworld-0.0.1.dist-info/top_level.txt
gpravada_helloworld-0.0.1.dist-info/RECORD
