Metadata-Version: 2.1
Name: gpravada-helloworld
Version: 0.0.1
Summary: Say Hello
Home-page: https://github.com/gpravada/gpravada-helloworld
Author: Gopi Ravada
Author-email: gp.ravada@gmail.com
License: UNKNOWN
Platform: UNKNOWN
Requires-Dist: blessings (~=1.7)
Provides-Extra: dev
Requires-Dist: pytest (>=3.7) ; extra == 'dev'
